[
    {
        "repository_name": "tesseract",
        "hash": "0a3a351cb3f321f61148cb3fd0dc94590b85f6f7",
        "author": "Egor Pugin",
        "date": "2019-08-17T08:31:54+03:00",
        "message": "Merge pull request #2620 from stweil/simd\n\nsimd: Check whether the OS supports FMA, AVX, ...",
        "modified_files_count": 1,
        "modified_files": [
            "src/arch/simddetect.cpp"
        ],
        "github_commit_url": "https://github.com/tesseract-ocr/tesseract/commit/0a3a351cb3f321f61148cb3fd0dc94590b85f6f7",
        "contains_optimization_keyword": true,
        "modified_func_count": 1,
        "modified_other": false,
        "modified_func": [
            "SIMDDetect::SIMDDetect"
        ],
        "added_lines": 3,
        "deleted_lines": 2,
        "total_changed_lines": 5,
        "net_line_change": 1,
        "modified_code_blocks": 3,
        "is_opt_ds_simple": "true"
    },
    {
        "repository_name": "tesseract",
        "hash": "24a29b79e5811b4d8a7ae9d81bc2ed7c83c8222a",
        "author": "Ger Hobbelt",
        "date": "2021-07-24T15:14:17+02:00",
        "message": "bugfix of FMA port to FAST_FLOAT\n\n8 float FPs fit in a single 256bit vector (8x32)\n(contrasting 4 double FPs: 4*64)\n\n[sw] Format commit message and use float instead of TFloat",
        "modified_files_count": 1,
        "modified_files": [
            "src/arch/dotproductfma.cpp"
        ],
        "github_commit_url": "https://github.com/tesseract-ocr/tesseract/commit/24a29b79e5811b4d8a7ae9d81bc2ed7c83c8222a",
        "contains_optimization_keyword": true,
        "modified_func_count": 1,
        "modified_other": false,
        "modified_func": [
            "DotProductFMA"
        ],
        "added_lines": 8,
        "deleted_lines": 8,
        "total_changed_lines": 16,
        "net_line_change": 0,
        "modified_code_blocks": 5,
        "is_opt_ds_simple": "true"
    },
    {
        "repository_name": "tesseract",
        "hash": "46c887b77eb2f8a3c356e75b340c1c2286a9cfbb",
        "author": "Stefan Weil",
        "date": "2017-05-03T09:49:23+02:00",
        "message": "genericvector: Fix minimum size\n\nCommit 907de5995f698e2a01da25fa09f8cadaf31a095f tried to improve\nGenericVector, but missed a case where vectors with less than\nkDefaultVectorSize were allocated. This resulted in additional\nalloc / free operations.\n\nCommit a28b2a033df10010bba9c1f49d6410ad69b3cdde (before memory optimization)\noem 0: total heap usage: 739,238 allocs, 739,237 frees, 161,699,214 bytes allocated\noem 1: total heap usage: 690,182 allocs, 690,175 frees, 144,470,400 bytes allocated\noem 2: total heap usage: 728,213 allocs, 728,206 frees, 182,885,824 bytes allocated\n\nCommit fd3f8f9b2d8c9ebf72b20a9d254a8e5c6900461e without genericvector change\noem 0: total heap usage: 738,980 allocs, 738,979 frees, 161,697,150 bytes allocated\noem 1: total heap usage: 690,182 allocs, 690,175 frees, 144,470,400 bytes allocated\noem 2: total heap usage: 728,213 allocs, 728,206 frees, 182,885,824 bytes allocated\n=> Improvements for oem 0, no change for oem 1 and oem 2.\n\nCommit fd3f8f9b2d8c9ebf72b20a9d254a8e5c6900461e\noem 0: total heap usage: 772,648 allocs, 772,647 frees, 160,083,901 bytes allocated\noem 1: total heap usage: 748,591 allocs, 748,584 frees, 143,581,672 bytes allocated\noem 2: total heap usage: 764,796 allocs, 764,789 frees, 181,212,197 bytes allocated\n=> Less bytes allocated, but more allocs / frees = bad for performance.\n\nCommit fd3f8f9b2d8c9ebf72b20a9d254a8e5c6900461e with this patch\noem 0: total heap usage: 677,537 allocs, 677,536 frees, 160,444,634 bytes allocated\noem 1: total heap usage: 653,812 allocs, 653,805 frees, 143,423,008 bytes allocated\noem 2: total heap usage: 670,029 allocs, 670,022 frees, 181,517,760 bytes allocated\n=> Improvements for all three cases.\n\nSigned-off-by: Stefan Weil <sw@weilnetz.de>",
        "modified_files_count": 1,
        "modified_files": [
            "ccutil/genericvector.h"
        ],
        "github_commit_url": "https://github.com/tesseract-ocr/tesseract/commit/46c887b77eb2f8a3c356e75b340c1c2286a9cfbb",
        "contains_optimization_keyword": true,
        "modified_func_count": 1,
        "modified_other": false,
        "modified_func": [
            "if"
        ],
        "added_lines": 1,
        "deleted_lines": 0,
        "total_changed_lines": 1,
        "net_line_change": 1,
        "modified_code_blocks": 1,
        "is_opt_ds_simple": "true"
    },
    {
        "repository_name": "tesseract",
        "hash": "88d4028a5a44e3fd7d0d66fe187b197ffccccf4e",
        "author": "Stefan Weil",
        "date": "2021-07-15T16:03:43+02:00",
        "message": "Enable pragma for SIMD also when _OPENMP is defined\n\nSigned-off-by: Stefan Weil <sw@weilnetz.de>",
        "modified_files_count": 1,
        "modified_files": [
            "src/arch/dotproduct.cpp"
        ],
        "github_commit_url": "https://github.com/tesseract-ocr/tesseract/commit/88d4028a5a44e3fd7d0d66fe187b197ffccccf4e",
        "contains_optimization_keyword": true,
        "modified_func_count": 1,
        "modified_other": false,
        "modified_func": [
            "DotProductNative"
        ],
        "added_lines": 1,
        "deleted_lines": 1,
        "total_changed_lines": 2,
        "net_line_change": 0,
        "modified_code_blocks": 1,
        "is_opt_ds_simple": "true"
    },
    {
        "repository_name": "tesseract",
        "hash": "92cae8f19418d13a0b698d8cd9b866ee0d3867b8",
        "author": "Stefan Weil",
        "date": "2021-08-12T14:44:45+02:00",
        "message": "Optimize check for non empty string\n\nSigned-off-by: Stefan Weil <sw@weilnetz.de>",
        "modified_files_count": 1,
        "modified_files": [
            "src/ccutil/ambigs.cpp"
        ],
        "github_commit_url": "https://github.com/tesseract-ocr/tesseract/commit/92cae8f19418d13a0b698d8cd9b866ee0d3867b8",
        "contains_optimization_keyword": true,
        "modified_func_count": 1,
        "modified_other": false,
        "modified_func": [
            "UnicharAmbigs::LoadUnicharAmbigs"
        ],
        "added_lines": 1,
        "deleted_lines": 1,
        "total_changed_lines": 2,
        "net_line_change": 0,
        "modified_code_blocks": 1,
        "is_opt_ds_simple": "true"
    },
    {
        "repository_name": "tesseract",
        "hash": "bb2348bbbe177389d7f5109e8ea1431ab3a9eda2",
        "author": "Stefan Weil",
        "date": "2017-05-12T14:15:54+02:00",
        "message": "genericvector: Fix and optimize function LoadDataFromFile\n\nIt's not necessary to initialize the vector with 0,\nbecause the initial values are read from file.\n\nFix also an assertion when trying to read an empty file.\n\nSigned-off-by: Stefan Weil <sw@weilnetz.de>",
        "modified_files_count": 1,
        "modified_files": [
            "ccutil/genericvector.h"
        ],
        "github_commit_url": "https://github.com/tesseract-ocr/tesseract/commit/bb2348bbbe177389d7f5109e8ea1431ab3a9eda2",
        "contains_optimization_keyword": true,
        "modified_func_count": 1,
        "modified_other": false,
        "modified_func": [
            "LoadDataFromFile"
        ],
        "added_lines": 11,
        "deleted_lines": 7,
        "total_changed_lines": 18,
        "net_line_change": 4,
        "modified_code_blocks": 2,
        "is_opt_ds_simple": "true"
    },
    {
        "repository_name": "tesseract",
        "hash": "f9860cda41fea6edce542c15dc17688efb0e5451",
        "author": "Stefan Weil",
        "date": "2019-03-24T21:21:23+01:00",
        "message": "Optimize functions ResetFrom\n\nThe loop can terminate as soon as the parameter name was found.\n\nSigned-off-by: Stefan Weil <sw@weilnetz.de>",
        "modified_files_count": 1,
        "modified_files": [
            "src/ccutil/params.h"
        ],
        "github_commit_url": "https://github.com/tesseract-ocr/tesseract/commit/f9860cda41fea6edce542c15dc17688efb0e5451",
        "contains_optimization_keyword": true,
        "modified_func_count": 1,
        "modified_other": false,
        "modified_func": [
            "ResetFrom"
        ],
        "added_lines": 4,
        "deleted_lines": 1,
        "total_changed_lines": 5,
        "net_line_change": 3,
        "modified_code_blocks": 5,
        "is_opt_ds_simple": "true"
    }
]