[
    {
        "repository_name": "Magisk",
        "hash": "5682917356e679e42941f21fcda82574bdd176a4",
        "author": "Chaosmaster",
        "date": "2021-11-03T22:22:29-07:00",
        "message": "Speed up zopfli compression\n\nSee #4810 for example",
        "modified_files_count": 1,
        "modified_files": [
            "native/jni/magiskboot/compress.cpp"
        ],
        "github_commit_url": "https://github.com/topjohnwu/Magisk/commit/5682917356e679e42941f21fcda82574bdd176a4",
        "contains_optimization_keyword": true,
        "modified_func_count": 1,
        "modified_other": false,
        "modified_func": [
            "std::move"
        ],
        "added_lines": 4,
        "deleted_lines": 0,
        "total_changed_lines": 4,
        "net_line_change": 4,
        "modified_code_blocks": 1,
        "is_opt_ds_simple": "true"
    }
]