[
    {
        "repository_name": "jq",
        "hash": "4b7c701fdd3f3e0bbbbe63c5df821f4145ff2b63",
        "author": "Nicolas Williams",
        "date": "2014-06-22T00:24:02-05:00",
        "message": "Tail call optimization (close #437)",
        "modified_files_count": 1,
        "modified_files": [
            "execute.c"
        ],
        "github_commit_url": "https://github.com/jqlang/jq/commit/4b7c701fdd3f3e0bbbbe63c5df821f4145ff2b63",
        "contains_optimization_keyword": true,
        "modified_func_count": 1,
        "modified_other": false,
        "modified_func": [
            "jq_next"
        ],
        "added_lines": 15,
        "deleted_lines": 4,
        "total_changed_lines": 19,
        "net_line_change": 11,
        "modified_code_blocks": 1,
        "is_opt_ds_simple": "true"
    },
    {
        "repository_name": "jq",
        "hash": "9b91eafac4df406e48348e2cb0baf6fcb998a6fa",
        "author": "Stephen Dolan",
        "date": "2013-05-16T15:09:59+01:00",
        "message": "Make array construction use LOADVN (slightly faster)",
        "modified_files_count": 1,
        "modified_files": [
            "compile.c"
        ],
        "github_commit_url": "https://github.com/jqlang/jq/commit/9b91eafac4df406e48348e2cb0baf6fcb998a6fa",
        "contains_optimization_keyword": true,
        "modified_func_count": 1,
        "modified_other": false,
        "modified_func": [
            "gen_collect"
        ],
        "added_lines": 1,
        "deleted_lines": 1,
        "total_changed_lines": 2,
        "net_line_change": 0,
        "modified_code_blocks": 1,
        "is_opt_ds_simple": "true"
    },
    {
        "repository_name": "jq",
        "hash": "beb0d081bb158678084c727cfdaef257f9c7b710",
        "author": "Nicolas Williams",
        "date": "2014-06-23T19:59:00-05:00",
        "message": "Improve TCO\n\nInstead of checking for self-recursion check that the thing we're\ncalling is a function and not a closure, therefore the new frame will\nhave the same env as the current frame.",
        "modified_files_count": 1,
        "modified_files": [
            "execute.c"
        ],
        "github_commit_url": "https://github.com/jqlang/jq/commit/beb0d081bb158678084c727cfdaef257f9c7b710",
        "contains_optimization_keyword": true,
        "modified_func_count": 1,
        "modified_other": false,
        "modified_func": [
            "jq_next"
        ],
        "added_lines": 1,
        "deleted_lines": 1,
        "total_changed_lines": 2,
        "net_line_change": 0,
        "modified_code_blocks": 1,
        "is_opt_ds_simple": "true"
    }
]